doc/sphinx/source/conf.py
gromacs/__init__.py
gromacs/cbook.py
gromacs/collections.py
gromacs/config.py
gromacs/core.py
gromacs/environment.py
gromacs/exceptions.py
gromacs/formats.py
gromacs/log.py
gromacs/qsub.py
gromacs/run.py
gromacs/scaling.py
gromacs/setup.py
gromacs/tools.py
gromacs/utilities.py
gromacs/fileformats/__init__.py
gromacs/fileformats/blocks.py
gromacs/fileformats/convert.py
gromacs/fileformats/mdp.py
gromacs/fileformats/ndx.py
gromacs/fileformats/top.py
gromacs/fileformats/xpm.py
gromacs/fileformats/xvg.py
gromacs/templates/darwin.sh
gromacs/templates/em.mdp
gromacs/templates/gromacswrapper.cfg
gromacs/templates/gromacswrapper_465.cfg
gromacs/templates/local.sh
gromacs/templates/md_CHARMM27.mdp
gromacs/templates/md_CHARMM27_gpu.mdp
gromacs/templates/md_G43a1.mdp
gromacs/templates/md_OPLSAA.mdp
gromacs/templates/md_OPLSAA_gpu.mdp
gromacswrapper-0.9.2.dist-info/licenses/COPYING
tests/fileformats/__init__.py
tests/fileformats/test_convert.py
tests/fileformats/test_mdp.py
tests/fileformats/test_ndx.py
tests/fileformats/test_xpm.py
tests/fileformats/test_xvg.py
tests/fileformats/top/__init__.py
tests/fileformats/top/test_TOP.py
tests/fileformats/top/test_amber03star.py
tests/fileformats/top/test_amber03w.py
tests/fileformats/top/test_charmm22.py
tests/fileformats/top/top.py
gromacswrapper-0.9.2.dist-info/METADATA
gromacswrapper-0.9.2.dist-info/WHEEL
gromacswrapper-0.9.2.dist-info/top_level.txt
gromacswrapper-0.9.2.dist-info/RECORD
