Metadata-Version: 2.4
Name: GromacsWrapper
Version: 0.9.2
Summary: A Python wrapper around the GROMACS tools.
Author-email: Oliver Beckstein <orbeckst@gmail.com>
License-Expression: GPL-3.0-or-later
Project-URL: homepage, https://github.com/Becksteinlab/GromacsWrapper
Project-URL: documentation, https://GromacsWrapper.readthedocs.org/
Project-URL: repository, https://github.com/Becksteinlab/GromacsWrapper
Project-URL: bug-tracker, https://github.com/Becksteinlab/GromacsWrapper/issues
Keywords: science,Gromacs,analysis,molecular dynamics
Classifier: Development Status :: 6 - Mature
Classifier: Environment :: Console
Classifier: Intended Audience :: Science/Research
Classifier: Operating System :: POSIX
Classifier: Operating System :: MacOS :: MacOS X
Classifier: Operating System :: Microsoft :: Windows
Classifier: Programming Language :: Python :: 3
Classifier: Programming Language :: Python :: 3.9
Classifier: Programming Language :: Python :: 3.10
Classifier: Programming Language :: Python :: 3.11
Classifier: Programming Language :: Python :: 3.12
Classifier: Programming Language :: Python :: 3.13
Classifier: Topic :: Scientific/Engineering :: Bio-Informatics
Classifier: Topic :: Scientific/Engineering :: Chemistry
Classifier: Topic :: Software Development :: Libraries :: Python Modules
Requires-Python: >=3.9
License-File: COPYING
Requires-Dist: matplotlib
Requires-Dist: numkit
Requires-Dist: numpy>=1.0
Provides-Extra: test
Requires-Dist: pytest; extra == "test"
Requires-Dist: pytest-cov; extra == "test"
Requires-Dist: setuptools; python_version >= "3.12" and extra == "test"
Requires-Dist: pandas>=0.17; extra == "test"
Dynamic: license-file
